pydykit/__init__.py
pydykit/_version.py
pydykit/abstract_base_classes.py
pydykit/configuration.py
pydykit/discrete_gradients.py
pydykit/examples.py
pydykit/factories.py
pydykit/integrators.py
pydykit/managers.py
pydykit/models.py
pydykit/models_integrators.py
pydykit/models_simulators.py
pydykit/models_system_dae.py
pydykit/models_system_multibody.py
pydykit/models_system_port_hamiltonian.py
pydykit/models_time_steppers.py
pydykit/operators.py
pydykit/plotters.py
pydykit/postprocessors.py
pydykit/results.py
pydykit/settings.py
pydykit/simulators.py
pydykit/solvers.py
pydykit/systems.py
pydykit/systems_dae.py
pydykit/systems_multi_body.py
pydykit/systems_port_hamiltonian.py
pydykit/time_steppers.py
pydykit/utils.py
pydykit/example_files/four_particle_system_discrete_gradient_dissipative.yml
pydykit/example_files/four_particle_system_midpoint.yml
pydykit/example_files/four_particle_system_ph_discrete_gradient_dissipative.yml
pydykit/example_files/four_particle_system_ph_midpoint.yml
pydykit/example_files/lorenz.yml
pydykit/example_files/pendulum_2d.yml
pydykit/example_files/pendulum_3d.yml
pydykit/example_files/reactor.yml
pydykit/example_files/rigid_body_rotating_quaternion.yml
pydykit/example_files/two_particle_system.yml
pydykit/example_files/visco_pendulum.yml
pydykit-0.0.5.dist-info/LICENSE
pydykit-0.0.5.dist-info/METADATA
pydykit-0.0.5.dist-info/WHEEL
pydykit-0.0.5.dist-info/top_level.txt
pydykit-0.0.5.dist-info/RECORD
