Metadata-Version: 2.2
Name: pydykit
Version: 0.0.5
Summary: pydykit: A Python-based dynamics simulation toolkit.
Author: Philipp L. Kinon, Julian Karl Bauer
Maintainer: Philipp L. Kinon, Julian Karl Bauer
Classifier: Development Status :: 4 - Beta
Classifier: Programming Language :: Python
Requires-Python: >=3.12
License-File: LICENSE
Requires-Dist: numpy
Requires-Dist: pandas
Requires-Dist: plotly
Requires-Dist: scipy
Requires-Dist: pyyaml
Requires-Dist: pydantic
Requires-Dist: pytest
